pyshn/__init__.py
pyshn/__main__.py
pyshn/cli.py
pyshn/cnpj.py
pyshn/cpf.py
pyshn-0.2.0.dist-info/LICENSE
pyshn-0.2.0.dist-info/METADATA
pyshn-0.2.0.dist-info/WHEEL
pyshn-0.2.0.dist-info/entry_points.txt
pyshn-0.2.0.dist-info/top_level.txt
pyshn-0.2.0.dist-info/RECORD
