Metadata-Version: 2.1
Name: pyshn
Version: 0.2.0
Summary: My python swiss army knife
Home-page: https://github.com/shneiderfku/pyshn/
Author: Rafael Ribeiro
Author-email: shneiderfku@outlook.com
License: MIT
Project-URL: Issue Tracker, https://github.com/shneiderfku/pyshn/issues/
Project-URL: Source Code, https://github.com/shneiderfku/pyshn/
Project-URL: Twitter, https://twitter.com/shneiderfku/
Platform: UNKNOWN
Classifier: Intended Audience :: Developers
Classifier: License :: OSI Approved :: MIT License
Classifier: Operating System :: OS Independent
Classifier: Programming Language :: Python :: 3.9
Classifier: Topic :: Software Development :: Libraries
Requires-Python: >=3.9
